py_wanderer/__init__.py
py_wanderer/algorithms.py
py_wanderer/heuristics.py
py_wanderer/maze.py
py_wanderer/plotter.py
py_wanderer-1.0.4.dist-info/LICENSE
py_wanderer-1.0.4.dist-info/WHEEL
py_wanderer-1.0.4.dist-info/METADATA
py_wanderer-1.0.4.dist-info/RECORD
